README.md
setup.py
lner/__init__.py
lner.egg-info/PKG-INFO
lner.egg-info/SOURCES.txt
lner.egg-info/dependency_links.txt
lner.egg-info/requires.txt
lner.egg-info/top_level.txt