Metadata-Version: 2.1
Name: lner
Version: 0.1.0
Summary: Lingorithm Named Entity Recognition
Home-page: https://github.com/lingorithm/lner
Author: Mohamed Mahrous
Author-email: m.mahrous.94@gmail.com
License: MIT
Platform: UNKNOWN
Classifier: Development Status :: 2 - Pre-Alpha
Classifier: Natural Language :: Arabic
Classifier: Intended Audience :: Developers
Classifier: Programming Language :: Python :: 3
Classifier: License :: OSI Approved :: MIT License
Classifier: Operating System :: OS Independent
Classifier: Topic :: Text Processing :: Linguistic
